MANIFEST.in
README.md
setup.py
hfilesize/__init__.py
hfilesize/hfilesize.py
hfilesize.egg-info/PKG-INFO
hfilesize.egg-info/SOURCES.txt
hfilesize.egg-info/dependency_links.txt
hfilesize.egg-info/top_level.txt