Metadata-Version: 1.1
Name: hfilesize
Version: 0.1.0
Summary: Human Readable File Sizes
Home-page: https://github.com/simonzack/hfilesize
Author: simonzack
Author-email: simonzack@gmail.com
License: GPLv3
Platform: UNKNOWN
Classifier: Development Status :: 4 - Beta
Classifier: License :: OSI Approved :: GNU General Public License v3 (GPLv3)
Classifier: Programming Language :: Python :: 3
Classifier: Topic :: Software Development :: Libraries :: Python Modules
